framenet_video_utils/__init__.py
framenet_video_utils/core.py
framenet_video_utils-1.0.1.dist-info/licenses/LICENSE
framenet_video_utils-1.0.1.dist-info/METADATA
framenet_video_utils-1.0.1.dist-info/WHEEL
framenet_video_utils-1.0.1.dist-info/top_level.txt
framenet_video_utils-1.0.1.dist-info/RECORD
