Metadata-Version: 2.4
Name: framenet-video-utils
Version: 1.0.1
Summary: A simple utility to get details like duration, resolution, and FPS from a video file.
Author-email: Surendra Kumar Reddy <surendraruka514@gmail.com>
License: MIT License
Project-URL: Homepage, https://www.framenet.ai
Project-URL: Documentation, https://github.com/Ruka-Surendra-Kumar-Reddy/framenet-video-utils/
Project-URL: Repository, https://github.com/Ruka-Surendra-Kumar-Reddy/framenet-video-utils/
Project-URL: Bug Tracker, https://github.com/Ruka-Surendra-Kumar-Reddy/framenet-video-utils/issues
Keywords: video,utils,ffmpeg,moviepy,framenet,video editing
Classifier: Programming Language :: Python :: 3
Classifier: License :: OSI Approved :: MIT License
Classifier: Operating System :: OS Independent
Classifier: Topic :: Multimedia :: Video
Classifier: Topic :: Software Development :: Libraries :: Python Modules
Requires-Python: >=3.7
License-File: LICENSE
Requires-Dist: moviepy
Dynamic: license-file
